woodelf/__init__.py
woodelf/api.py
woodelf/constants.py
woodelf/util.py
woodelf/core/__init__.py
woodelf/core/editor.py
woodelf/core/element.py
woodelf/core/elf.py
woodelf/core/section.py
woodelf/core/segment.py
woodelf/core/transaction.py
woodelf/editors/__init__.py
woodelf/editors/dynamic_entry_editor.py
woodelf/editors/elf_header_editor.py
woodelf/editors/program_header_editor.py
woodelf/editors/section_header_editor.py
woodelf/editors/strtab_editor.py
woodelf/editors/symbol_editor.py
woodelf/editors/symbol_version_editor.py
woodelf/elements/__init__.py
woodelf/elements/dynamic_entry.py
woodelf/elements/e_ident.py
woodelf/elements/elf_header.py
woodelf/elements/gnu_hash.py
woodelf/elements/program_header.py
woodelf/elements/section_header.py
woodelf/elements/symbol.py
woodelf/elements/symbol_version.py
woodelf-0.1.0.dist-info/METADATA
woodelf-0.1.0.dist-info/WHEEL
woodelf-0.1.0.dist-info/top_level.txt
woodelf-0.1.0.dist-info/RECORD
