Metadata-Version: 2.1
Name: woodelf
Version: 0.1.0
Summary: Pure Python ELF file parser
Author: Donghwi Kim
Author-email: dhkim09@kaist.ac.kr
Requires-Python: >=3.9
Requires-Dist: sh
Requires-Dist: hexdump
Provides-Extra: test
Requires-Dist: sh ; extra == 'test'
Requires-Dist: hexdump ; extra == 'test'
